LICENSE
MANIFEST.in
README.md
discrete.py
setup.py
discrete.egg-info/PKG-INFO
discrete.egg-info/SOURCES.txt
discrete.egg-info/dependency_links.txt
discrete.egg-info/top_level.txt