Metadata-Version: 1.1
Name: discrete
Version: 0.0.2
Summary: Pure Python implementation of discrete random variables
Home-page: https://gitlab.com/TC01/python-discrete
Author: Ben Rosser
Author-email: rosser.bjr@gmail.com
License: MIT
Keywords: discrete random probability
Platform: UNKNOWN
Classifier: Development Status :: 2 - Pre-Alpha
Classifier: Intended Audience :: Developers
Classifier: Intended Audience :: Science/Research
Classifier: License :: OSI Approved :: MIT License
Classifier: Programming Language :: Python :: 2
Classifier: Programming Language :: Python :: 2.7
Classifier: Programming Language :: Python :: 3
Classifier: Programming Language :: Python :: 3.3
Classifier: Programming Language :: Python :: 3.4
Classifier: Programming Language :: Python :: 3.5
Classifier: Topic :: Scientific/Engineering :: Mathematics
